django_extensions/__init__.py
django_extensions/apps.py
django_extensions/collision_resolvers.py
django_extensions/compat.py
django_extensions/import_subclasses.py
django_extensions/models.py
django_extensions/settings.py
django_extensions/validators.py
django_extensions/admin/__init__.py
django_extensions/admin/filter.py
django_extensions/admin/widgets.py
django_extensions/auth/__init__.py
django_extensions/auth/mixins.py
django_extensions/conf/app_template/__init__.py.tmpl
django_extensions/conf/app_template/forms.py.tmpl
django_extensions/conf/app_template/models.py.tmpl
django_extensions/conf/app_template/urls.py.tmpl
django_extensions/conf/app_template/views.py.tmpl
django_extensions/conf/app_template/migrations/__init__.py.tmpl
django_extensions/conf/command_template/management/__init__.py.tmpl
django_extensions/conf/command_template/management/commands/__init__.py.tmpl
django_extensions/conf/command_template/management/commands/sample.py.tmpl
django_extensions/conf/jobs_template/jobs/__init__.py.tmpl
django_extensions/conf/jobs_template/jobs/sample.py.tmpl
django_extensions/conf/jobs_template/jobs/daily/__init__.py.tmpl
django_extensions/conf/jobs_template/jobs/hourly/__init__.py.tmpl
django_extensions/conf/jobs_template/jobs/monthly/__init__.py.tmpl
django_extensions/conf/jobs_template/jobs/weekly/__init__.py.tmpl
django_extensions/conf/jobs_template/jobs/yearly/__init__.py.tmpl
django_extensions/conf/template_tags_template/templatetags/__init__.py.tmpl
django_extensions/conf/template_tags_template/templatetags/sample.py.tmpl
django_extensions/db/__init__.py
django_extensions/db/models.py
django_extensions/db/fields/__init__.py
django_extensions/db/fields/json.py
django_extensions/jobs/__init__.py
django_extensions/jobs/daily/__init__.py
django_extensions/jobs/daily/cache_cleanup.py
django_extensions/jobs/daily/daily_cleanup.py
django_extensions/jobs/hourly/__init__.py
django_extensions/jobs/minutely/__init__.py
django_extensions/jobs/monthly/__init__.py
django_extensions-3.2.1.dist-info/LICENSE
django_extensions-3.2.1.dist-info/METADATA
django_extensions-3.2.1.dist-info/WHEEL
django_extensions-3.2.1.dist-info/top_level.txt
django_extensions-3.2.1.dist-info/RECORD
