Metadata-Version: 2.1
Name: django-extensions
Version: 3.2.1
Summary: Extensions for Django
Home-page: http://github.com/django-extensions/django-extensions
Author: Michael Trier
Author-email: mtrier@gmail.com
Maintainer: Bas van Oostveen
Maintainer-email: v.oostveen@gmail.com
License: MIT License
Project-URL: Documentation, https://django-extensions.readthedocs.io/
Project-URL: Changelog, https://github.com/django-extensions/django-extensions/blob/main/CHANGELOG.md
Project-URL: Source, https://github.com/django-extensions/django-extensions
Project-URL: Tracker, https://github.com/django-extensions/django-extensions/issues
Platform: any
Classifier: Development Status :: 5 - Production/Stable
Classifier: Environment :: Web Environment
Classifier: Framework :: Django
Classifier: Framework :: Django :: 3.2
Classifier: Framework :: Django :: 4.0
Classifier: Framework :: Django :: 4.1
Classifier: Intended Audience :: Developers
Classifier: License :: OSI Approved :: MIT License
Classifier: Operating System :: OS Independent
Classifier: Programming Language :: Python
Classifier: Programming Language :: Python :: 3
Classifier: Programming Language :: Python :: 3 :: Only
Classifier: Programming Language :: Python :: 3.6
Classifier: Programming Language :: Python :: 3.7
Classifier: Programming Language :: Python :: 3.8
Classifier: Programming Language :: Python :: 3.9
Classifier: Programming Language :: Python :: 3.10
Classifier: Programming Language :: Python :: Implementation :: CPython
Classifier: Programming Language :: Python :: Implementation :: PyPy
Classifier: Topic :: Utilities
Requires-Python: >=3.6
License-File: LICENSE
